orinoco/__init__.py
orinoco/action.py
orinoco/condition.py
orinoco/data_source.py
orinoco/entities.py
orinoco/event.py
orinoco/exceptions.py
orinoco/helpers.py
orinoco/loop.py
orinoco/observers.py
orinoco/py.typed
orinoco/retry.py
orinoco/settings.py
orinoco/tags.py
orinoco/transformation.py
orinoco/typed_action.py
orinoco/types.py
orinoco-2.0.0.dist-info/METADATA
orinoco-2.0.0.dist-info/WHEEL
orinoco-2.0.0.dist-info/RECORD
